setup.py
v2ray/__init__.py
v2ray/v2ray_init.py
v2ray/v2ray_ping.py
v2ray_ping.egg-info/PKG-INFO
v2ray_ping.egg-info/SOURCES.txt
v2ray_ping.egg-info/dependency_links.txt
v2ray_ping.egg-info/entry_points.txt
v2ray_ping.egg-info/top_level.txt