Metadata-Version: 1.1
Name: v2ray-ping
Version: 1.0.0
Summary: a ping tool for v2ray mac client,find fast vpn server for you
Home-page: https://github.com/JoeSteven/v2rayPro-speed
Author: Joey
Author-email: qiaoxiaoxi621@gmail.com
License: Apache 2.0
Keywords: v2ray
Platform: UNKNOWN
Classifier: Development Status :: 4 - Beta
Classifier: License :: OSI Approved :: Apache Software License
Classifier: Programming Language :: Python :: 3
Classifier: Operating System :: OS Independent
Classifier: Intended Audience :: System Administrators
Classifier: Topic :: System :: Networking :: Monitoring
Classifier: Topic :: Utilities
